{
  "name": "图节点_output",
  "domain": "graph",
  "owner": "aok",
  "version": "1.0.0",
  "description": "事务 图节点_output",
  "tags": [],
  "docs": {
    "md_path": "autodokit/affairs/图节点_output/affair.md"
  },
  "runner": {
    "module": "autodokit.affairs.图节点_output.affair",
    "callable": "execute",
    "pass_mode": "config_path",
    "kwargs": {}
  },
  "interface": {
    "inputs": [],
    "outputs": []
  },
  "config": {
    "defaults": {},
    "required": []
  },
  "legacy": {
    "module_aliases": [
      "autodokit.affairs.graph_node_output"
    ]
  },
  "node": {
    "node_type": "output",
    "affair_type": "graph_node_output_v1",
    "config": {
      "output_name": "output",
      "output_target": ""
    },
    "payload_defaults": {},
    "inputs": {
      "data": {
        "name": "data",
        "data_type": "any"
      }
    },
    "outputs": {},
    "allow_multi_input_ports": [],
    "is_leaf": true,
    "is_business": false,
    "is_graph": true
  }
}
